timeit_resource/__init__.py
timeit_resource/timeit_resource.py
timeit_resource-0.0.1.dist-info/LICENSE
timeit_resource-0.0.1.dist-info/METADATA
timeit_resource-0.0.1.dist-info/WHEEL
timeit_resource-0.0.1.dist-info/top_level.txt
timeit_resource-0.0.1.dist-info/RECORD
