Metadata-Version: 2.1
Name: timeit-resource
Version: 0.0.1
Summary: TimeIt Resource to easily capture and report time consumed by code snippets.
Home-page: https://github.com/arunsundaram50/timeit-resource.git
Author: Arun Sundaram
Author-email: arun_co@yahoo.com
License-File: LICENSE
